pytumblrx/__init__.py
pytumblrx/_about.py
pytumblrx/_client_mixin.py
pytumblrx/_defaults.py
pytumblrx/async_client.py
pytumblrx/endpoints.py
pytumblrx/enums.py
pytumblrx/exceptions.py
pytumblrx/request.py
pytumblrx/sync_client.py
pytumblrx-0.0.4.dist-info/LICENSE
pytumblrx-0.0.4.dist-info/METADATA
pytumblrx-0.0.4.dist-info/WHEEL
pytumblrx-0.0.4.dist-info/RECORD
